sdanalyzer/__init__.py
sdanalyzer/app.py
sdanalyzer/forms.py
sdanalyzer/main.py
sdanalyzer/utils.py
sdanalyzer/data/rules.yar
sdanalyzer/data/trusted_certs.csv
sdanalyzer/templates/apk_show.html
sdanalyzer/templates/index.html
sdanalyzer/templates/layout.html
sdanalyzer/templates/phones_new.html
sdanalyzer/templates/phones_show.html
sdanalyzer-0.1.7.dist-info/LICENSE
sdanalyzer-0.1.7.dist-info/METADATA
sdanalyzer-0.1.7.dist-info/WHEEL
sdanalyzer-0.1.7.dist-info/entry_points.txt
sdanalyzer-0.1.7.dist-info/top_level.txt
sdanalyzer-0.1.7.dist-info/RECORD
