Metadata-Version: 2.1
Name: sdanalyzer
Version: 0.1.7
Summary: Tool to analyze APK files
Home-page: https://github.com/Te-k/sdanalyzer
Author: Tek
Author-email: tek@randhome.io
License: GPLv3
Keywords: osint
Platform: UNKNOWN
Classifier: Programming Language :: Python :: 3
Classifier: License :: OSI Approved :: MIT License
Classifier: Operating System :: OS Independent
Requires-Python: >=3.5
License-File: LICENSE
Requires-Dist: Flask (==2.2.2)
Requires-Dist: Flask-WTF (==1.0.1)
Requires-Dist: peewee (==3.15.2)
Requires-Dist: androguard (==3.3.5)
Requires-Dist: requests
Requires-Dist: yara-python (==4.2.3)
